LICENSE.txt
MANIFEST.in
README.md
pyproject.toml
requirements.txt
setup.cfg
setup.py
platypush/__init__.py
platypush/__main__.py
platypush/cli.py
platypush/components.json.gz
platypush/logger.py
platypush.egg-info/PKG-INFO
platypush.egg-info/SOURCES.txt
platypush.egg-info/dependency_links.txt
platypush.egg-info/entry_points.txt
platypush.egg-info/requires.txt
platypush.egg-info/top_level.txt
platypush/app/__init__.py
platypush/app/__main__.py
platypush/app/_app.py
platypush/backend/__init__.py
platypush/backend/http/__init__.py
platypush/backend/http/manifest.json
platypush/backend/http/utils.py
platypush/backend/http/app/__init__.py
platypush/backend/http/app/mixins/__init__.py
platypush/backend/http/app/routes/__init__.py
platypush/backend/http/app/routes/auth.py
platypush/backend/http/app/routes/dashboard.py
platypush/backend/http/app/routes/execute.py
platypush/backend/http/app/routes/hook.py
platypush/backend/http/app/routes/index.py
platypush/backend/http/app/routes/logo.py
platypush/backend/http/app/routes/logout.py
platypush/backend/http/app/routes/otp.py
platypush/backend/http/app/routes/plugin.py
platypush/backend/http/app/routes/pwa.py
platypush/backend/http/app/routes/resources.py
platypush/backend/http/app/routes/plugins/__init__.py
platypush/backend/http/app/routes/plugins/spotify.py
platypush/backend/http/app/routes/plugins/camera/__init__.py
platypush/backend/http/app/routes/plugins/camera/pi.py
platypush/backend/http/app/routes/plugins/qrcode/__init__.py
platypush/backend/http/app/routes/plugins/tts/__init__.py
platypush/backend/http/app/streaming/__init__.py
platypush/backend/http/app/streaming/_base.py
platypush/backend/http/app/streaming/plugins/__init__.py
platypush/backend/http/app/streaming/plugins/camera.py
platypush/backend/http/app/streaming/plugins/file.py
platypush/backend/http/app/streaming/plugins/sound.py
platypush/backend/http/app/streaming/plugins/media/__init__.py
platypush/backend/http/app/streaming/plugins/media/_constants.py
platypush/backend/http/app/streaming/plugins/media/_register.py
platypush/backend/http/app/streaming/plugins/media/_registry.py
platypush/backend/http/app/streaming/plugins/media/_stream.py
