Metadata-Version: 2.4
Name: platypush
Version: 1.3.7
Summary: A general-purpose framework for automation
Author-email: Fabio Manganiello <fabio@manganiello.tech>
Project-URL: homepage, https://platypush.tech
Project-URL: repository, https://git.platypush.tech/platypush/platypush
Project-URL: documentation, https://docs.platypush.tech
Project-URL: blog, https://blog.platypush.tech
Keywords: home-automation,automation,iot,mqtt,websockets,redis,dashboard,notifications
Classifier: Topic :: Utilities
Classifier: License :: OSI Approved :: MIT License
Classifier: Development Status :: 4 - Beta
Requires-Python: >=3.6
License-File: LICENSE.txt
Requires-Dist: alembic
Requires-Dist: croniter
Requires-Dist: docutils
Requires-Dist: flask
Requires-Dist: marshmallow<4.0.0a0
Requires-Dist: Pillow
Requires-Dist: python-dateutil
Requires-Dist: python-magic
Requires-Dist: pygments
Requires-Dist: pyotp
Requires-Dist: pyyaml
Requires-Dist: pyzbar
Requires-Dist: qrcode
Requires-Dist: redis
Requires-Dist: requests
Requires-Dist: rsa
Requires-Dist: sqlalchemy
Requires-Dist: tornado
Requires-Dist: watchdog
Requires-Dist: websocket-client
Requires-Dist: websockets
Requires-Dist: zeroconf>=0.27.0
Requires-Dist: werkzeug>=3.0.1
Requires-Dist: zipp>=3.19.1
Requires-Dist: urllib3>=2.2.2
Provides-Extra: nodered
Requires-Dist: pynodered; extra == "nodered"
Provides-Extra: tts
Requires-Dist: num2words; extra == "tts"
Requires-Dist: numpy; extra == "tts"
Requires-Dist: sounddevice; extra == "tts"
Provides-Extra: tts-mimic3
Requires-Dist: numpy; extra == "tts-mimic3"
Requires-Dist: sounddevice; extra == "tts-mimic3"
Provides-Extra: tts-picovoice
Requires-Dist: numpy; extra == "tts-picovoice"
Requires-Dist: pvorca; extra == "tts-picovoice"
Requires-Dist: sounddevice; extra == "tts-picovoice"
Provides-Extra: tts-google
Requires-Dist: sounddevice; extra == "tts-google"
Requires-Dist: google-cloud-texttospeech; extra == "tts-google"
Requires-Dist: numpy; extra == "tts-google"
Provides-Extra: tts-openai
Requires-Dist: numpy; extra == "tts-openai"
Requires-Dist: sounddevice; extra == "tts-openai"
Provides-Extra: hid
Requires-Dist: hid; extra == "hid"
Provides-Extra: tv-samsung-ws
Requires-Dist: samsungtvws; extra == "tv-samsung-ws"
Provides-Extra: trello
Requires-Dist: py-trello; extra == "trello"
Provides-Extra: midi
Requires-Dist: rtmidi; extra == "midi"
Provides-Extra: matrix
Requires-Dist: matrix-nio[e2e]; extra == "matrix"
Requires-Dist: async_lru; extra == "matrix"
Provides-Extra: torrent
Requires-Dist: libtorrent; extra == "torrent"
Provides-Extra: http-webpage
Requires-Dist: weasyprint; extra == "http-webpage"
Provides-Extra: dropbox
Requires-Dist: dropbox; extra == "dropbox"
Provides-Extra: calendar-ical
Requires-Dist: icalendar; extra == "calendar-ical"
Provides-Extra: gpio
Requires-Dist: RPi.GPIO; extra == "gpio"
Provides-Extra: mqtt
Requires-Dist: paho-mqtt; extra == "mqtt"
Provides-Extra: telegram
Requires-Dist: python-telegram-bot; extra == "telegram"
Provides-Extra: arduino
Requires-Dist: pyfirmata2; extra == "arduino"
Provides-Extra: lcd-i2c
Requires-Dist: RPLCD; extra == "lcd-i2c"
Requires-Dist: RPi.GPIO; extra == "lcd-i2c"
Provides-Extra: lcd-gpio
Requires-Dist: RPLCD; extra == "lcd-gpio"
Requires-Dist: RPi.GPIO; extra == "lcd-gpio"
Provides-Extra: google-maps
Requires-Dist: google-api-python-client; extra == "google-maps"
Requires-Dist: google-auth; extra == "google-maps"
Requires-Dist: oauth2client; extra == "google-maps"
Requires-Dist: httplib2; extra == "google-maps"
Provides-Extra: google-calendar
Requires-Dist: google-api-python-client; extra == "google-calendar"
Requires-Dist: google-auth; extra == "google-calendar"
Requires-Dist: oauth2client; extra == "google-calendar"
Requires-Dist: httplib2; extra == "google-calendar"
Provides-Extra: google-pubsub
Requires-Dist: google-api-python-client; extra == "google-pubsub"
Requires-Dist: google-auth; extra == "google-pubsub"
Requires-Dist: oauth2client; extra == "google-pubsub"
Requires-Dist: google-cloud-pubsub; extra == "google-pubsub"
Requires-Dist: httplib2; extra == "google-pubsub"
Provides-Extra: google-mail
Requires-Dist: google-api-python-client; extra == "google-mail"
Requires-Dist: google-auth; extra == "google-mail"
Requires-Dist: oauth2client; extra == "google-mail"
Requires-Dist: httplib2; extra == "google-mail"
Provides-Extra: google-drive
Requires-Dist: google-api-python-client; extra == "google-drive"
Requires-Dist: google-auth; extra == "google-drive"
Requires-Dist: oauth2client; extra == "google-drive"
Requires-Dist: httplib2; extra == "google-drive"
Provides-Extra: google-translate
Requires-Dist: google-api-python-client; extra == "google-translate"
Requires-Dist: google-auth; extra == "google-translate"
Requires-Dist: oauth2client; extra == "google-translate"
Requires-Dist: google-cloud-translate; extra == "google-translate"
Requires-Dist: httplib2; extra == "google-translate"
Provides-Extra: kafka
Requires-Dist: kafka-python-ng; extra == "kafka"
Provides-Extra: clipboard
Requires-Dist: pyclip; extra == "clipboard"
Provides-Extra: switch-tplink
Requires-Dist: pyHS100; extra == "switch-tplink"
Provides-Extra: sound
Requires-Dist: sounddevice; extra == "sound"
Requires-Dist: numpy; extra == "sound"
Provides-Extra: rss
Requires-Dist: feedparser; extra == "rss"
Requires-Dist: defusedxml; extra == "rss"
Provides-Extra: mail
Requires-Dist: dnspython; extra == "mail"
Requires-Dist: imapclient; extra == "mail"
Provides-Extra: ssh
Requires-Dist: paramiko; extra == "ssh"
Provides-Extra: ngrok
Requires-Dist: pyngrok; extra == "ngrok"
Provides-Extra: youtube
Requires-Dist: yt-dlp; extra == "youtube"
Provides-Extra: system
Requires-Dist: py-cpuinfo; extra == "system"
Requires-Dist: psutil; extra == "system"
Provides-Extra: bluetooth
Requires-Dist: bleak; extra == "bluetooth"
Requires-Dist: bluetooth-numbers; extra == "bluetooth"
Requires-Dist: TheengsDecoder; extra == "bluetooth"
Requires-Dist: pydbus; extra == "bluetooth"
Provides-Extra: pwm-pca9685
Requires-Dist: adafruit-circuitpython-pca9685; extra == "pwm-pca9685"
Provides-Extra: light-hue
Requires-Dist: phue; extra == "light-hue"
Provides-Extra: adafruit-io
Requires-Dist: adafruit-io; extra == "adafruit-io"
Provides-Extra: nfc
Requires-Dist: nfcpy>=1.0; extra == "nfc"
Requires-Dist: ndeflib; extra == "nfc"
Provides-Extra: twilio
Requires-Dist: twilio; extra == "twilio"
Provides-Extra: gps
Requires-Dist: gps; extra == "gps"
Provides-Extra: music-tidal
Requires-Dist: tidalapi>=0.7.0; extra == "music-tidal"
Provides-Extra: music-mpd
Requires-Dist: python-mpd2; extra == "music-mpd"
Provides-Extra: tensorflow
Requires-Dist: numpy; extra == "tensorflow"
Requires-Dist: pandas; extra == "tensorflow"
Requires-Dist: tensorflow; extra == "tensorflow"
Requires-Dist: keras; extra == "tensorflow"
Provides-Extra: ffmpeg
Requires-Dist: ffmpeg-python; extra == "ffmpeg"
Provides-Extra: serial
Requires-Dist: pyserial; extra == "serial"
Provides-Extra: dbus
Requires-Dist: pydbus; extra == "dbus"
Requires-Dist: defusedxml; extra == "dbus"
Provides-Extra: nextcloud
Requires-Dist: nextcloud-api-wrapper; extra == "nextcloud"
Provides-Extra: assistant-picovoice
Requires-Dist: num2words; extra == "assistant-picovoice"
Requires-Dist: pvcheetah; extra == "assistant-picovoice"
Requires-Dist: pvleopard; extra == "assistant-picovoice"
Requires-Dist: pvorca; extra == "assistant-picovoice"
Requires-Dist: pvporcupine; extra == "assistant-picovoice"
Requires-Dist: pvrhino; extra == "assistant-picovoice"
Requires-Dist: sounddevice; extra == "assistant-picovoice"
Provides-Extra: assistant-google
Requires-Dist: google-assistant-library; extra == "assistant-google"
Requires-Dist: google-auth; extra == "assistant-google"
Requires-Dist: sounddevice; extra == "assistant-google"
Provides-Extra: assistant-openai
Requires-Dist: numpy; extra == "assistant-openai"
Requires-Dist: pydub; extra == "assistant-openai"
Requires-Dist: sounddevice; extra == "assistant-openai"
Provides-Extra: irc
Requires-Dist: irc; extra == "irc"
Provides-Extra: lastfm
Requires-Dist: pylast; extra == "lastfm"
Provides-Extra: zwave-mqtt
Requires-Dist: paho-mqtt; extra == "zwave-mqtt"
Provides-Extra: weather-buienradar
Requires-Dist: buienradar; extra == "weather-buienradar"
Provides-Extra: media-gstreamer
Requires-Dist: pygobject; extra == "media-gstreamer"
Provides-Extra: media-vlc
Requires-Dist: python-vlc; extra == "media-vlc"
Requires-Dist: yt-dlp; extra == "media-vlc"
Provides-Extra: media-plex
Requires-Dist: plexapi; extra == "media-plex"
Provides-Extra: media-subtitles
Requires-Dist: python-opensubtitles; extra == "media-subtitles"
Requires-Dist: webvtt-py; extra == "media-subtitles"
Provides-Extra: media-mpv
Requires-Dist: python-mpv; extra == "media-mpv"
Requires-Dist: yt-dlp; extra == "media-mpv"
Provides-Extra: media-chromecast
Requires-Dist: pychromecast; extra == "media-chromecast"
Provides-Extra: media-kodi
Requires-Dist: kodi-json; extra == "media-kodi"
Provides-Extra: cups
Requires-Dist: pycups; extra == "cups"
Provides-Extra: ml-cv
Requires-Dist: numpy; extra == "ml-cv"
Requires-Dist: opencv-python; extra == "ml-cv"
Provides-Extra: linode
Requires-Dist: linode_api4; extra == "linode"
Provides-Extra: todoist
Requires-Dist: todoist-python; extra == "todoist"
Provides-Extra: sensor-distance-vl53l1x
Requires-Dist: smbus2; extra == "sensor-distance-vl53l1x"
Requires-Dist: vl53l1x; extra == "sensor-distance-vl53l1x"
Provides-Extra: sensor-mcp3008
Requires-Dist: adafruit-mcp3008; extra == "sensor-mcp3008"
Provides-Extra: sensor-envirophat
Requires-Dist: envirophat; extra == "sensor-envirophat"
Provides-Extra: sensor-hcsr04
Requires-Dist: RPi.GPIO; extra == "sensor-hcsr04"
Provides-Extra: sensor-lis3dh
Requires-Dist: Adafruit-GPIO; extra == "sensor-lis3dh"
Provides-Extra: sensor-dht
Requires-Dist: Adafruit_Python_DHT; extra == "sensor-dht"
Provides-Extra: sensor-ltr559
Requires-Dist: ltr559; extra == "sensor-ltr559"
Requires-Dist: smbus; extra == "sensor-ltr559"
Provides-Extra: sensor-bme280
Requires-Dist: pimoroni-bme280; extra == "sensor-bme280"
Provides-Extra: sensor-pmw3901
Requires-Dist: pmw3901; extra == "sensor-pmw3901"
Provides-Extra: luma-oled
Requires-Dist: luma.oled; extra == "luma-oled"
Provides-Extra: zigbee-mqtt
Requires-Dist: paho-mqtt; extra == "zigbee-mqtt"
Provides-Extra: camera-gstreamer
Requires-Dist: numpy; extra == "camera-gstreamer"
Requires-Dist: Pillow; extra == "camera-gstreamer"
Requires-Dist: pygobject; extra == "camera-gstreamer"
Provides-Extra: camera-ffmpeg
Requires-Dist: numpy; extra == "camera-ffmpeg"
Requires-Dist: Pillow; extra == "camera-ffmpeg"
Provides-Extra: camera-ir-mlx90640
Requires-Dist: numpy; extra == "camera-ir-mlx90640"
Requires-Dist: Pillow; extra == "camera-ir-mlx90640"
Provides-Extra: camera-pi
Requires-Dist: picamera2; extra == "camera-pi"
Requires-Dist: numpy; extra == "camera-pi"
Requires-Dist: Pillow; extra == "camera-pi"
Provides-Extra: camera-pi-legacy
Requires-Dist: picamera; extra == "camera-pi-legacy"
Requires-Dist: numpy; extra == "camera-pi-legacy"
Requires-Dist: Pillow; extra == "camera-pi-legacy"
Provides-Extra: camera-cv
Requires-Dist: numpy; extra == "camera-cv"
Requires-Dist: opencv-python; extra == "camera-cv"
Requires-Dist: Pillow; extra == "camera-cv"
Provides-Extra: smartthings
Requires-Dist: pysmartthings; extra == "smartthings"
Dynamic: license-file
Dynamic: provides-extra
